macro_polo/__init__.py
macro_polo/__main__.py
macro_polo/_utils.py
macro_polo/codec.py
macro_polo/match.py
macro_polo/transcribe.py
macro_polo/macros/__init__.py
macro_polo/macros/decorator.py
macro_polo/macros/function.py
macro_polo/macros/importer.py
macro_polo/macros/macro_rules.py
macro_polo/macros/module.py
macro_polo/macros/predefined.py
macro_polo/macros/proc.py
macro_polo/macros/super.py
macro_polo/macros/types.py
macro_polo/parse/__init__.py
macro_polo/parse/_matchers.py
macro_polo/parse/_transcribers.py
macro_polo/parse/_utils.py
macro_polo.pth
macro_polo-0.3.0.dist-info/METADATA
macro_polo-0.3.0.dist-info/WHEEL
macro_polo-0.3.0.dist-info/licenses/LICENSE
macro_polo-0.3.0.dist-info/RECORD
