Metadata-Version: 2.4
Name: macro-polo
Version: 0.3.0
Summary: Rust-style macros for Python
Project-URL: Homepage, https://github.com/BenjyWiener/macro-polo
Project-URL: Repository, https://github.com/BenjyWiener/macro-polo
Project-URL: Documentation, https://macro-polo.readthedocs.com
Author: Benjy Wiener
License-Expression: MIT
License-File: LICENSE
Keywords: macros,preprocessor,rust
Classifier: Development Status :: 3 - Alpha
Classifier: Operating System :: OS Independent
Classifier: Programming Language :: Python :: 3
Classifier: Programming Language :: Python :: 3.12
Classifier: Programming Language :: Python :: 3.13
Classifier: Programming Language :: Python :: Implementation :: CPython
Classifier: Topic :: Software Development :: Pre-processors
Requires-Python: >=3.12
